acdh_xml_pyutils/__init__.py
acdh_xml_pyutils/xml.py
acdh_xml_pyutils/files/tei _no_xml_decl.xml
acdh_xml_pyutils/files/tei.xml
acdh_xml_pyutils/files/test.txt
acdh_xml_pyutils-1.1.1.dist-info/LICENSE
acdh_xml_pyutils-1.1.1.dist-info/METADATA
acdh_xml_pyutils-1.1.1.dist-info/WHEEL
acdh_xml_pyutils-1.1.1.dist-info/top_level.txt
acdh_xml_pyutils-1.1.1.dist-info/RECORD
