Metadata-Version: 2.1
Name: acdh-xml-pyutils
Version: 1.1.1
Summary: Utility functions to work with XML
Home-page: https://github.com/acdh-oeaw/acdh-xml-pyutils
Author: Peter Andorfer
Author-email: peter.andorfer@oeaw.ac.at
License: MIT
Keywords: acdh_xml_pyutils
Classifier: Development Status :: 2 - Pre-Alpha
Classifier: Intended Audience :: Developers
Classifier: License :: OSI Approved :: MIT License
Classifier: Natural Language :: English
Classifier: Programming Language :: Python :: 3
Classifier: Programming Language :: Python :: 3.7
Classifier: Programming Language :: Python :: 3.8
Requires-Python: >=3.7
License-File: LICENSE
Requires-Dist: lxml
Requires-Dist: requests
